cli.py
main.py
agents/__init__.py
agents/analyzer.py
agents/designer.py
agents/orchestrator.py
agents/workers/__init__.py
agents/workers/reviewer_worker.py
agents/workers/translator_worker.py
agents/workers/validator_worker.py
mcp_client/__init__.py
mcp_client/client.py
model/__init__.py
model/load.py
prompts/__init__.py
prompts/requirements.md
prompts/system_prompts.py
task_manager/__init__.py
task_manager/manager.py
task_manager/types.py
tools/__init__.py
tools/file_tools.py
wstranslator-0.1.38.dist-info/METADATA
wstranslator-0.1.38.dist-info/WHEEL
wstranslator-0.1.38.dist-info/entry_points.txt
wstranslator-0.1.38.dist-info/top_level.txt
wstranslator-0.1.38.dist-info/RECORD
