Metadata-Version: 2.4
Name: WsTranslator
Version: 0.1.38
Summary: Workshop Translator - AI-powered workshop document translation agent
Author-email: Jisan Bang <wltks2155@gmail.com>
License: MIT
Project-URL: Homepage, https://github.com/onesuit/workshop-translator
Project-URL: Repository, https://github.com/onesuit/workshop-translator
Project-URL: Issues, https://github.com/onesuit/workshop-translator/issues
Keywords: workshop,translator,ai,bedrock,aws,agentcore
Classifier: Development Status :: 3 - Alpha
Classifier: Intended Audience :: Developers
Classifier: License :: OSI Approved :: MIT License
Classifier: Programming Language :: Python :: 3
Classifier: Programming Language :: Python :: 3.10
Classifier: Programming Language :: Python :: 3.11
Classifier: Programming Language :: Python :: 3.12
Requires-Python: >=3.10
Requires-Dist: aws-opentelemetry-distro>=0.10.0
Requires-Dist: bedrock-agentcore>=1.0.3
Requires-Dist: bedrock-agentcore-starter-toolkit
Requires-Dist: boto3>=1.34.0
Requires-Dist: mcp>=1.19.0
Requires-Dist: pytest>=7.0.0
Requires-Dist: pytest-asyncio>=0.21.0
Requires-Dist: python-dotenv>=1.2.1
Requires-Dist: pyyaml>=6.0
Requires-Dist: strands-agents>=1.13.0
Requires-Dist: strands-agents-tools>=0.2.16
Provides-Extra: remote
Requires-Dist: bedrock-agentcore>=1.0.3; extra == "remote"
